Metadata-Version: 2.1
Name: odoo-addon-account-portal-invoice-search-by-lot
Version: 15.0.1.0.0.6
Summary: Account Portal Invoice Search By Lot
Home-page: https://github.com/OCA/account-invoicing
Author: Tecnativa, Odoo Community Association (OCA)
Author-email: support@odoo-community.org
License: AGPL-3
Platform: UNKNOWN
Classifier: Programming Language :: Python
Classifier: Framework :: Odoo
Classifier: Framework :: Odoo :: 15.0
Classifier: License :: OSI Approved :: GNU Affero General Public License v3
Classifier: Development Status :: 4 - Beta
Requires-Python: >=3.8
Requires-Dist: odoo-addon-account-portal-invoice-search <15.1dev,>=15.0dev
Requires-Dist: odoo <15.1dev,>=15.0a
